{
    "ios-uuid":{
        "URL":"http://xuyafei.com/post/all/ios-uuid",
        "Title":"iOS 中的设备唯一标识",
        "FuzzyMatch":[],
        "ExactMatch":[],
        "RelatedURL":{
            "Weibo":"",
            "Jinashu":"",
            "Github":""
        }
    },
    "ios10.3-comment":{
        "URL":"http://xuyafei.com/post/all/ios10.3-comment",
        "Title":"iOS10.3 的评论系统",
        "FuzzyMatch":[],
        "ExactMatch":[
            "ios10.3de-ping-lun-xi-tong"
        ],
        "RelatedURL":{
            "Weibo":"",
            "Jinashu":"",
            "Github":""
        }
    },
    "swift-accessmodifier":{
        "URL":"http://xuyafei.com/post/all/swift-accessmodifier",
        "Title":"Swift 中的访问控制",
        "FuzzyMatch":[],
        "ExactMatch":[
            "swiftzhong-de-fang-wen-kong-zhi"
        ],
        "RelatedURL":{
            "Weibo":"",
            "Jinashu":"",
            "Github":""
        }
    },
    "ios-thread":{
        "URL":"http://xuyafei.com/post/all/ios-thread",
        "Title":"iOS 中的多线程技术",
        "FuzzyMatch":[],
        "ExactMatch":[
            "ioszhong-de-duo-xian-cheng-ji-zhu"
        ],
        "RelatedURL":{
            "Weibo":"",
            "Jinashu":"",
            "Github":""
        }
    },
    "webview-finishload":{
        "URL":"http://xuyafei.com/post/all/webview-finishload",
        "Title":"如何准确判断 WebView 加载完成",
        "FuzzyMatch":["webview"],
        "ExactMatch":[
            "webviewdidfinishload"
        ],
        "RelatedURL":{
            "Weibo":"",
            "Jinashu":"",
            "Github":""
        }
    },
    "webview-typesetting":{
        "URL":"http://xuyafei.com/post/all/webview-typesetting",
        "Title":"使用 WebView + HTML + JavaScript + JSExport 实现图文混排",
        "FuzzyMatch":[],
        "ExactMatch":[
            "tu-wen-hun-pai"
        ],
        "RelatedURL":{
            "Weibo":"",
            "Jinashu":"",
            "Github":""
        }
    },
    "assistivetouch":{
        "URL":"http://xuyafei.com/post/all/assistivetouch",
        "Title":"开源工具 XFAssistiveTouch",
        "FuzzyMatch":[],
        "ExactMatch":[
            "assistivetouch"
        ],
        "RelatedURL":{
            "Weibo":"http://weibo.com/1750985774/DyST3Czzc",
            "Jinashu":"",
            "Github":"https://github.com/xiaofei86/XFAssistiveTouch"
        }
    },
    "quartz2d1":{
        "URL":"http://xuyafei.com/post/all/quartz2d1",
        "Title":"Quartz2D 编程指南（一）概览、图形上下文、路径、颜色与颜色空间",
        "FuzzyMatch":["quartz"],
        "ExactMatch":[
            "quartz2dbian-cheng-zhi-nan-1",
            "quartz2d-bian-cheng-zhi-nan-gai-lan-tu-xing-shang-xia-wen-lu-jing-yan-se-yu-yan-se-kong-jian"
        ],
        "RelatedURL":{
            "Weibo":"",
            "Jinashu":"",
            "Github":""
        }
    },
    "quartz2d2":{
        "URL":"http://xuyafei.com/post/all/quartz2d2",
        "Title":"Quartz2D 编程指南（二）变换、图案、阴影",
        "FuzzyMatch":["quartz"],
        "ExactMatch":[
            "quartz2dbian-cheng-zhi-nan-2",
            "quartz2d-bian-cheng-zhi-nan-er-bian-huan-tu-an-yin-ying"
        ],
        "RelatedURL":{
            "Weibo":"",
            "Jinashu":"",
            "Github":""
        }
    },
    "quartz2d3":{
        "URL":"http://xuyafei.com/post/all/quartz2d3",
        "Title":"Quartz2D 编程指南（三）渐变、透明层 、数据管理",
        "FuzzyMatch":["quartz"],
        "ExactMatch":[
            "quartz2dbian-cheng-zhi-nan-3",
            "quartz2d-bian-cheng-zhi-nan-san-jian-bian-tou-ming-ceng-shu-ju-guan-li"
        ],
        "RelatedURL":{
            "Weibo":"",
            "Jinashu":"",
            "Github":""
        }
    },
    "quartz2d4":{
        "URL":"http://xuyafei.com/post/all/quartz2d4",
        "Title":"Quartz2D 编程指南（四）位图与图像遮罩、CoreGraphics 绘制 Layer",
        "FuzzyMatch":["quartz"],
        "ExactMatch":[
            "quartz2dbian-cheng-zhi-nan-4",
            "quartz2d-bian-cheng-zhi-nan-si-wei-tu-yu-tu-xiang-zhe-zhao-coregraphics-hui-zhi-layer"
        ],
        "RelatedURL":{
            "Weibo":"",
            "Jinashu":"",
            "Github":""
        }
    },
    "navigationbar":{
        "URL":"http://xuyafei.com/post/all/navigationbar",
        "Title":"透明与半透明 NavigationBar 切换的三种方案",
        "FuzzyMatch":[],
        "ExactMatch":[
            "navigationbar"
        ],
        "RelatedURL":{
            "Weibo":"",
            "Jinashu":"",
            "Github":""
        }
    },
    "memory-alignment":{
        "URL":"http://xuyafei.com/post/all/memory-alignment",
        "Title":"内存对齐",
        "FuzzyMatch":[],
        "ExactMatch":[
            "nei-cun-dui-qi"
        ],
        "RelatedURL":{
            "Weibo":"",
            "Jinashu":"",
            "Github":""
        }
    },
    "ios-shortcut":{
        "URL":"http://xuyafei.com/post/all/ios-shortcut",
        "Title":"iOS 开发常用快捷键",
        "FuzzyMatch":[],
        "ExactMatch":[
            "ioskai-fa-chang-yong-kuai-jie-jian"
        ],
        "RelatedURL":{
            "Weibo":"",
            "Jinashu":"",
            "Github":""
        }
    },
    "r-property-declare":{
        "URL":"http://xuyafei.com/post/all/r-property-declare",
        "Title":"[转]属性声明在implementation与extension的使用规范",
        "FuzzyMatch":[],
        "ExactMatch":[
            "-zhuan-shu-xing-sheng-ming-gui-fan",
            "shu-xing-sheng-ming-zai-implementationyu-extensionde-shi-yong-gui-fan"
        ],
        "RelatedURL":{
            "Weibo":"",
            "Jinashu":"",
            "Github":""
        }
    },
    "codeguide1-named":{
        "URL":"http://xuyafei.com/post/all/codeguide1-named",
        "Title":"Cocoa代码风格指南之命名规范（一）",
        "FuzzyMatch":[],
        "ExactMatch":[
            "dai-ma-gui-fan-1ming-ming-gui-fan",
            "cocoadai-ma-feng-ge-zhi-nan-zhi-ming-ming-gui-fan"
        ],
        "RelatedURL":{
            "Weibo":"",
            "Jinashu":"",
            "Github":""
        }
    },
    "codeguide2-typesetting":{
        "URL":"http://xuyafei.com/post/all/codeguide2-typesetting",
        "Title":"Cocoa代码风格指南之排版规范（二）",
        "FuzzyMatch":[],
        "ExactMatch":[
            "dai-ma-gui-fan-2pai-ban-gui-fan",
            "cocoadai-ma-feng-ge-zhi-nan-zhi-pai-ban-gui-fan-er"
        ],
        "RelatedURL":{
            "Weibo":"",
            "Jinashu":"",
            "Github":""
        }
    },
    "codeguide3-comment":{
        "URL":"http://xuyafei.com/post/all/codeguide3-comment",
        "Title":"Cocoa代码风格指南之注释规范（三）",
        "FuzzyMatch":[],
        "ExactMatch":[
            "dai-ma-gui-fan-3zhu-shi-gui-fan",
            "cocoadai-ma-feng-ge-zhi-nan-zhi-zhu-shi-gui-fan-san"
        ],
        "RelatedURL":{
            "Weibo":"",
            "Jinashu":"",
            "Github":""
        }
    },
    "codeguide4-usage":{
        "URL":"http://xuyafei.com/post/all/codeguide4-usage",
        "Title":"Cocoa代码风格指南之使用规范（四）",
        "FuzzyMatch":[],
        "ExactMatch":[
            "dai-ma-gui-fan-4shi-yong-gui-fan",
            "cocoadai-ma-feng-ge-zhi-nan-zhi-shi-yong-gui-fan-si"
        ],
        "RelatedURL":{
            "Weibo":"",
            "Jinashu":"",
            "Github":""
        }
    },
    "integer":{
        "URL":"http://xuyafei.com/post/all/integer",
        "Title":"整型数的使用规范",
        "FuzzyMatch":[],
        "ExactMatch":[
            "zheng-xing-shu-shi-yong-gui-fan",
            "zheng-xing-shu-de-shi-yong-gui-fan"
        ],
        "RelatedURL":{
            "Weibo":"",
            "Jinashu":"",
            "Github":""
        }
    },
    "cocoapod1-install":{
        "URL":"http://xuyafei.com/post/all/cocoapod1-install",
        "Title":"CocoaPods的安装与使用（一）",
        "FuzzyMatch":["cocoapod"],
        "ExactMatch":[
            "cocoapod1an-zhuang-yu-shi-yong",
            "cocoapodsde-an-zhuang-yu-shi-yong"
        ],
        "RelatedURL":{
            "Weibo":"",
            "Jinashu":"",
            "Github":""
        }
    },
    "cocoapod2-impl":{
        "URL":"http://xuyafei.com/post/all/cocoapod2-impl",
        "Title":"CocoaPods的原理与技巧（二）",
        "FuzzyMatch":["cocoapod"],
        "ExactMatch":[
            "cocoapod2yuan-li-yu-ji-qiao",
            "cocoapodsde-yuan-li-yu-ji-qiao-er"
        ],
        "RelatedURL":{
            "Weibo":"",
            "Jinashu":"",
            "Github":""
        }
    },
    "cocoapod3-podspec":{
        "URL":"http://xuyafei.com/post/all/cocoapod3-podspec",
        "Title":"ocoaPods建立自己的Podspec（三）",
        "FuzzyMatch":["cocoapod"],
        "ExactMatch":[
            "cocoapod3jian-li-podspec",
            "cocoapodsjian-li-zi-ji-de-podspec-san"
        ],
        "RelatedURL":{
            "Weibo":"",
            "Jinashu":"",
            "Github":""
        }
    },
    "cocoapod4-story":{
        "URL":"http://xuyafei.com/post/all/cocoapod4-story",
        "Title":"CocoaPods诞生的时代背景（四）",
        "FuzzyMatch":["cocoapod"],
        "ExactMatch":[
            "cocoapod4shi-dai-bei-jing",
            "cocoapodsdan-sheng-de-shi-dai-bei-jing-si"
        ],
        "RelatedURL":{
            "Weibo":"",
            "Jinashu":"",
            "Github":""
        }
    },
    "cocoapod-verify":{
        "URL":"http://xuyafei.com/post/private/cocoapod-verify",
        "Title":"CocoaPods下载原理的验证过程",
        "FuzzyMatch":["cocoapod"],
        "ExactMatch":[
            "cocoapodsxia-zai-yuan-li-de-yan-zheng-guo-cheng"
        ],
        "RelatedURL":{
            "Weibo":"",
            "Jinashu":"",
            "Github":""
        }
    },
    "cggeometry":{
        "URL":"http://xuyafei.com/post/all/cggeometry",
        "Title":"使用 CGGeometry 方法获取 CGRect 数据",
        "FuzzyMatch":[],
        "ExactMatch":[
            "cggeometry",
            "shi-yong-cggeometryfang-fa-huo-qu-cgrectshu-ju"
        ],
        "RelatedURL":{
            "Weibo":"",
            "Jinashu":"",
            "Github":""
        }
    },
    "autolayout-layout":{
        "URL":"http://xuyafei.com/post/all/autolayout-layout",
        "Title":"UIView 在 AutoLayout 下的布局过程",
        "FuzzyMatch":[],
        "ExactMatch":[
            "autolayoutbu-ju-guo-cheng"
        ],
        "RelatedURL":{
            "Weibo":"",
            "Jinashu":"",
            "Github":""
        }
    },
    "property-modifier":{
        "URL":"http://xuyafei.com/post/all/property-modifier",
        "Title":"属性内存管理相关修饰符的使用规范",
        "FuzzyMatch":[],
        "ExactMatch":[
            "shu-xing-xiu-shi-fu-gui-fan",
            "shu-xing-nei-cun-guan-li-xiang-guan-xiu-shi-fu-de-shi-yong-gui-fan"
        ],
        "RelatedURL":{
            "Weibo":"",
            "Jinashu":"",
            "Github":""
        }
    }
}